_mlpfile.cpython-311-i386-linux-musl.so
mlpfile/_codegen.py
mlpfile/__init__.py
mlpfile/torch/__init__.py
mlpfile/torch/torch.py
mlpfile/cpp/mlpfile.h
mlpfile/cpp/mlpfile.cpp
mlpfile.libs/libstdc++-8baf04f9.so.6.0.28
mlpfile.libs/libgcc_s-8b50eaaa.so.1
mlpfile-0.3.0.dist-info/top_level.txt
mlpfile-0.3.0.dist-info/METADATA
mlpfile-0.3.0.dist-info/WHEEL
mlpfile-0.3.0.dist-info/RECORD
