Metadata-Version: 2.1
Name: mlpfile
Version: 0.3.0
Summary: Multilayer perceptron file format and evaluation.
Home-page: https://github.com/jpreiss/mlpfile
Author: James A. Preiss
Author-email: jamesalanpreiss@gmail.com
Requires: numpy
Requires-Python: >=3.7
Provides-Extra: test
Requires-Dist: pytest ; extra == 'test'
Requires-Dist: torch ; extra == 'test'
Provides-Extra: torch
Requires-Dist: torch ; extra == 'torch'
